django_sorl_async_thumbnails-0.1.1.dist-info/licenses/LICENSE
sorl_async_thumbnails/__init__.py
sorl_async_thumbnails/apps.py
sorl_async_thumbnails/backend.py
sorl_async_thumbnails/conf.py
sorl_async_thumbnails/defaults.py
sorl_async_thumbnails/tasks.py
django_sorl_async_thumbnails-0.1.1.dist-info/METADATA
django_sorl_async_thumbnails-0.1.1.dist-info/WHEEL
django_sorl_async_thumbnails-0.1.1.dist-info/top_level.txt
django_sorl_async_thumbnails-0.1.1.dist-info/RECORD
