Metadata-Version: 2.4
Name: django-sorl-async-thumbnails
Version: 0.1.1
Summary: Asynchronous thumbnail generation for sorl-thumbnail using Celery
Home-page: https://github.com/alex-msk/sorl_async_thumbnails
Author: Alex
Author-email: web@2347.ru
Classifier: Development Status :: 4 - Beta
Classifier: Framework :: Django
Classifier: Framework :: Django :: 3.2
Classifier: Framework :: Django :: 4.0
Classifier: Framework :: Django :: 4.1
Classifier: Framework :: Django :: 4.2
Classifier: Intended Audience :: Developers
Classifier: License :: OSI Approved :: MIT License
Classifier: Programming Language :: Python :: 3
Classifier: Programming Language :: Python :: 3.8
Classifier: Programming Language :: Python :: 3.9
Classifier: Programming Language :: Python :: 3.10
Classifier: Programming Language :: Python :: 3.11
Requires-Python: >=3.8
License-File: LICENSE
Requires-Dist: Django>=3.2
Requires-Dist: sorl-thumbnail>=12.9.0
Requires-Dist: celery>=5.0.0
Dynamic: author
Dynamic: author-email
Dynamic: classifier
Dynamic: description
Dynamic: description-content-type
Dynamic: home-page
Dynamic: license-file
Dynamic: requires-dist
Dynamic: requires-python
Dynamic: summary
